HIRID_MEDS/__init__.py
HIRID_MEDS/__main__.py
HIRID_MEDS/commands.py
HIRID_MEDS/dataset.yaml
HIRID_MEDS/download.py
HIRID_MEDS/pre_MEDS.py
HIRID_MEDS/configs/ETL.yaml
HIRID_MEDS/configs/__init__.py
HIRID_MEDS/configs/event_configs.yaml
HIRID_MEDS/configs/main.yaml
HIRID_MEDS/configs/pre_MEDS.yaml
HIRID_MEDS/configs/runner.yaml
hirid_meds-0.0.3.dist-info/licenses/LICENSE
hirid_meds-0.0.3.dist-info/METADATA
hirid_meds-0.0.3.dist-info/WHEEL
hirid_meds-0.0.3.dist-info/entry_points.txt
hirid_meds-0.0.3.dist-info/top_level.txt
hirid_meds-0.0.3.dist-info/RECORD
