Metadata-Version: 2.4
Name: HIRID-MEDS
Version: 0.0.3
Summary: An ETL pipeline to extract HIRID data into the MEDS format.
Author-email: Robin van de Water <robin.vandewater@hpi.de>
Project-URL: Homepage, https://github.com/mmcdermott/ETL_MEDS_Template
Project-URL: Issues, https://github.com/mmcdermott/ETL_MEDS_Template/issues
Classifier: Programming Language :: Python :: 3
Classifier: License :: OSI Approved :: MIT License
Classifier: Operating System :: OS Independent
Requires-Python: >=3.11
License-File: LICENSE
Requires-Dist: meds-transforms~=0.2.4
Requires-Dist: requests
Requires-Dist: beautifulsoup4
Requires-Dist: hydra-core
Requires-Dist: loguru
Requires-Dist: polars<1.30.0
Provides-Extra: dev
Requires-Dist: pre-commit<4; extra == "dev"
Provides-Extra: tests
Requires-Dist: pytest; extra == "tests"
Requires-Dist: pytest-cov; extra == "tests"
Provides-Extra: local-parallelism
Requires-Dist: hydra-joblib-launcher; extra == "local-parallelism"
Provides-Extra: slurm-parallelism
Requires-Dist: hydra-submitit-launcher; extra == "slurm-parallelism"
Dynamic: license-file
